FaceC/__init__.py
FaceC/faceBox.py
FaceC-0.0.2.dist-info/LICENSE
FaceC-0.0.2.dist-info/METADATA
FaceC-0.0.2.dist-info/WHEEL
FaceC-0.0.2.dist-info/top_level.txt
FaceC-0.0.2.dist-info/RECORD
